JWST_FOV_plotter/FOV_transform.py
JWST_FOV_plotter/__init__.py
JWST_FOV_plotter/apertures_selecter.py
JWST_FOV_plotter/auxiliar_functions.py
JWST_FOV_plotter/fovs_loader.py
JWST_FOV_plotter/inst_coverage.py
JWST_FOV_plotter/plotter.py
JWST_FOV_plotter/data/Aper_translation.csv
JWST_FOV_plotter/data/SIAF_V2V3_FOVs.csv
jwst_fov_plotter-0.4.1.dist-info/LICENSE
jwst_fov_plotter-0.4.1.dist-info/METADATA
jwst_fov_plotter-0.4.1.dist-info/WHEEL
jwst_fov_plotter-0.4.1.dist-info/top_level.txt
jwst_fov_plotter-0.4.1.dist-info/RECORD
