Metadata-Version: 2.2
Name: JWST_FOV_plotter
Version: 0.4.1
Summary: Simple tools to easily represent JWST FOVs.
Home-page: https://gitlab.com/parrabalh/jwst_fov_plots
Author: Pablo Arrabal Haro
Author-email: parrabalh@gmail.com
License: LICENSE
Classifier: Programming Language :: Python :: 3
Classifier: License :: OSI Approved :: MIT License
Classifier: Operating System :: OS Independent
Requires-Python: >=3
License-File: LICENSE
Requires-Dist: astropy
Requires-Dist: matplotlib
Requires-Dist: numpy
Requires-Dist: pandas
Requires-Dist: shapely
Dynamic: author
Dynamic: author-email
Dynamic: classifier
Dynamic: description
Dynamic: description-content-type
Dynamic: home-page
Dynamic: license
Dynamic: requires-dist
Dynamic: requires-python
Dynamic: summary
